MySQL_E/__init__.py
MySQL_E/core.py
MySQL_E/database.py
mysql_easy_connector_python-0.12.dist-info/METADATA
mysql_easy_connector_python-0.12.dist-info/WHEEL
mysql_easy_connector_python-0.12.dist-info/top_level.txt
mysql_easy_connector_python-0.12.dist-info/RECORD
